newql/VERSION
newql/__init__.py
newql/context.py
newql/dev_server.py
newql/errors.py
newql/example.py
newql/field.py
newql/introspection.py
newql/parse.py
newql/schema.py
newql-0.6.0.dist-info/LICENSE
newql-0.6.0.dist-info/METADATA
newql-0.6.0.dist-info/WHEEL
newql-0.6.0.dist-info/top_level.txt
newql-0.6.0.dist-info/RECORD
