Metadata-Version: 2.1
Name: newql
Version: 0.6.0
Summary: A simplified GraphQL-esque library
Home-page: https://github.com/nayaverdier/newql
Author: Naya Verdier
License: MIT
Platform: UNKNOWN
Classifier: Programming Language :: Python
Classifier: Programming Language :: Python :: 3
Requires-Python: >=3.7
License-File: LICENSE
Requires-Dist: parsimonious (>=0.8)
Requires-Dist: varname (~=0.6)
Requires-Dist: typing-inspect ; python_version <= "3.7"
Provides-Extra: dev
Requires-Dist: black (==21.6b0) ; extra == 'dev'
Requires-Dist: coverage (==5.5) ; extra == 'dev'
Requires-Dist: flake8 (==3.9.2) ; extra == 'dev'
Requires-Dist: flake8-bugbear (==21.4.3) ; extra == 'dev'
Requires-Dist: isort (==5.9.1) ; extra == 'dev'
Requires-Dist: mypy (==0.910) ; extra == 'dev'
Requires-Dist: pytest (==6.2.4) ; extra == 'dev'
Requires-Dist: pytest-cov (==2.12.1) ; extra == 'dev'
Requires-Dist: twine (==3.4.1) ; extra == 'dev'
